 [
  {
  "letterImage": "a",
  "letterWordImage": "b_a",
  "letterExampleImage": "alcha",
  "audioLetter": "a",
  "audioWord": "alcha",
  },
  {
  "letterImage": "b",
  "letterWordImage": "b_b",
  "letterExampleImage": "bugu",
  "audioLetter": "b",
  "audioWord": "bugu",
  },
  {
  "letterImage": "v",
  "letterWordImage": "b_v",
  "letterExampleImage": "velosiped",
  "audioLetter": "v",
  "audioWord": "velosiped",
  },
  {
  "letterImage": "g",
  "letterWordImage": "b_g",
  "letterExampleImage": "gul",
  "audioLetter": "g",
  "audioWord": "gul",
  },
  {
  "letterImage": "d",
  "letterWordImage": "b_d",
  "letterExampleImage": "darbyz",
  "audioLetter": "d",
  "audioWord": "darbyz",
  },
  {
  "letterImage": "e",
  "letterWordImage": "b_e",
  "letterExampleImage": "a_jeyren",
  "audioLetter": "e",
  "audioWord": "jeyren",
  },
  {
  "letterImage": "yo",
  "letterWordImage": "b_yo",
  "letterExampleImage": "koyon",
  "audioLetter": "yo",
  "audioWord": "yokoen",
  },
  {
  "letterImage": "j",
  "letterWordImage": "b_j",
  "letterExampleImage": "jolbors",
  "audioLetter": "j",
  "audioWord": "jolbors",
  },
  {
  "letterImage": "z",
  "letterWordImage": "b_z",
  "letterExampleImage": "zym",
  "audioLetter": "z",
  "audioWord": "zym",
  },
  {
  "letterImage": "i",
  "letterWordImage": "b_i",
  "letterExampleImage": "it",
  "audioLetter": "i",
  "audioWord": "it",
  },
  {
  "letterImage": "iy",
  "letterWordImage": "b_iy",
  "letterExampleImage": "yod",
  "audioLetter": "iy",
  "audioWord": "iyod",
  },
  {
  "letterImage": "k",
  "letterWordImage": "b_k",
  "letterExampleImage": "kayik",
  "audioLetter": "k",
  "audioWord": "kayuk",
  },
  {
  "letterImage": "l",
  "letterWordImage": "b_l",
  "letterExampleImage": "limon",
  "audioLetter": "l",
  "audioWord": "limon",
  },
  {
  "letterImage": "m",
  "letterWordImage": "b_m",
  "letterExampleImage": "a_maymyl",
  "audioLetter": "m",
  "audioWord": "maymyl",
  },
  {
  "letterImage": "n",
  "letterWordImage": "b_n",
  "letterExampleImage": "nan",
  "audioLetter": "n",
  "audioWord": "nan",
  },
  {
  "letterImage": "ny",
  "letterWordImage": "b_nn",
  "letterExampleImage": "dongolok",
  "audioLetter": "nn",
  "audioWord": "dongolok",
  },
  {
  "letterImage": "o",
  "letterWordImage": "b_o",
  "letterExampleImage": "orok",
  "audioLetter": "o",
  "audioWord": "orok",
  },
  {
  "letterImage": "oo",
  "letterWordImage": "b_oo",
  "letterExampleImage": "ordok",
  "audioLetter": "oo",
  "audioWord": "oordok",
  },
  {
  "letterImage": "p",
  "letterWordImage": "b_p",
  "letterExampleImage": "piyaz",
  "audioLetter": "p",
  "audioWord": "piyaz",
  },
  {
  "letterImage": "r",
  "letterWordImage": "b_r",
  "letterExampleImage": "raketa",
  "audioLetter": "r",
  "audioWord": "raketa",
  },
  {
  "letterImage": "s",
  "letterWordImage": "b_s",
  "letterExampleImage": "sandyk",
  "audioLetter": "s",
  "audioWord": "sandyk",
  },
  {
  "letterImage": "t",
  "letterWordImage": "b_t",
  "letterExampleImage": "took",
  "audioLetter": "t",
  "audioWord": "took",
  },
  {
  "letterImage": "u",
  "letterWordImage": "b_u",
  "letterExampleImage": "uy",
  "audioLetter": "u",
  "audioWord": "uy",
  },
  {
  "letterImage": "uu",
  "letterWordImage": "b_uu",
  "letterExampleImage": "yyi",
  "audioLetter": "yy",
  "audioWord": "yyi",
  },
  {
  "letterImage": "f",
  "letterWordImage": "b_f",
  "letterExampleImage": "fartuk",
  "audioLetter": "f",
  "audioWord": "fartuk",
  },
  {
  "letterImage": "h",
  "letterWordImage": "b_h",
  "letterExampleImage": "halat",
  "audioLetter": "h",
  "audioWord": "halat",
  },
  {
  "letterImage": "c",
  "letterWordImage": "b_c",
  "letterExampleImage": "cement",
  "audioLetter": "c",
  "audioWord": "cement",
  },
  {
  "letterImage": "ch",
  "letterWordImage": "b_ch",
  "letterExampleImage": "chychkan",
  "audioLetter": "ch",
  "audioWord": "chychkan",
  },
  {
  "letterImage": "sh",
  "letterWordImage": "b_sh",
  "letterExampleImage": "shypyrgy",
  "audioLetter": "sh",
  "audioWord": "shypyrgy",
  },
  {
  "letterImage": "sha",
  "letterWordImage": "b_sha",
  "letterExampleImage": "shetka",
  "audioLetter": "sh",
  "audioWord": "shetka",
  },
  {
  "letterImage": "tz",
  "letterWordImage": "b_tz",
  "letterExampleImage": "podiezd",
  "audioLetter": "tz",
  "audioWord": "tzpodyezd",
  },
  {
  "letterImage": "y",
  "letterWordImage": "b_y",
  "letterExampleImage": "yshkyryk",
  "audioLetter": "y",
  "audioWord": "yshkyryk",
  },
  {
  "letterImage": "mz",
  "letterWordImage": "b_mz",
  "letterExampleImage": "apelsin2",
  "audioLetter": "mz",
  "audioWord": "mzapelsin",
  },
  {
  "letterImage": "ee",
  "letterWordImage": "b_ee",
  "letterExampleImage": "elik",
  "audioLetter": "ee",
  "audioWord": "eelik",
  },
  {
  "letterImage": "yu",
  "letterWordImage": "b_yu",
  "letterExampleImage": "oyunchuk",
  "audioLetter": "yu",
  "audioWord": "oyunchuk",
  },
  {
  "letterImage": "ya",
  "letterWordImage": "b_ya",
  "letterExampleImage": "yahta",
  "audioLetter": "ya",
  "audioWord": "yahta",
  }
  ]